{
  "generated_at_utc": "2026-07-06T02:19:27.669554+00:00",
  "input_dir": "data/bronze",
  "bronze_dir": "data/bronze",
  "format": "parquet",
  "years": [
    2023,
    2024,
    2025
  ],
  "missing_files": [],
  "preservation_rule": "A camada bronze registra bases Parquet brutas, mantendo nomes de colunas, tipos e valores de origem sem padronizacao.",
  "files": [
    {
      "source": "data/bronze/ano=2023/TS_ALUNO.parquet",
      "target": "data/bronze/ano=2023/TS_ALUNO.parquet",
      "source_size_bytes": 23248334,
      "target_size_bytes": 23248334,
      "rows": 1747439,
      "columns": [
        "NU_ANO_AVALIACAO",
        "CO_UF",
        "SG_UF",
        "ID_ALUNO",
        "TP_SERIE",
        "ID_ESCOLA",
        "TP_DEPENDENCIA",
        "CO_MUNICIPIO",
        "NO_MUNICIPIO",
        "IN_PRESENCA_LP",
        "IN_PREENCHIMENTO_LP",
        "CO_CADERNO_LP",
        "VL_PESO_ALUNO_LP",
        "VL_PROFICIENCIA_LP",
        "IN_ALFABETIZADO"
      ],
      "column_types": {
        "NU_ANO_AVALIACAO": "int64",
        "CO_UF": "int64",
        "SG_UF": "string",
        "ID_ALUNO": "int64",
        "TP_SERIE": "int64",
        "ID_ESCOLA": "int64",
        "TP_DEPENDENCIA": "int64",
        "CO_MUNICIPIO": "int64",
        "NO_MUNICIPIO": "string",
        "IN_PRESENCA_LP": "int64",
        "IN_PREENCHIMENTO_LP": "int64",
        "CO_CADERNO_LP": "int64",
        "VL_PESO_ALUNO_LP": "double",
        "VL_PROFICIENCIA_LP": "double",
        "IN_ALFABETIZADO": "int64"
      },
      "ano_safra": 2023,
      "table": "TS_ALUNO"
    },
    {
      "source": "data/bronze/ano=2023/TS_ESTADO.parquet",
      "target": "data/bronze/ano=2023/TS_ESTADO.parquet",
      "source_size_bytes": 6100,
      "target_size_bytes": 6100,
      "rows": 70,
      "columns": [
        "NU_ANO_AVALIACAO",
        "CO_UF",
        "SG_UF",
        "TP_SERIE",
        "ID_TIPO_REDE",
        "PC_ALUNO_ALFABETIZADO",
        "VL_MEDIA_LP"
      ],
      "column_types": {
        "NU_ANO_AVALIACAO": "int64",
        "CO_UF": "int64",
        "SG_UF": "string",
        "TP_SERIE": "int64",
        "ID_TIPO_REDE": "int64",
        "PC_ALUNO_ALFABETIZADO": "double",
        "VL_MEDIA_LP": "double"
      },
      "ano_safra": 2023,
      "table": "TS_ESTADO"
    },
    {
      "source": "data/bronze/ano=2023/TS_ITEM.parquet",
      "target": "data/bronze/ano=2023/TS_ITEM.parquet",
      "source_size_bytes": 41337,
      "target_size_bytes": 41337,
      "rows": 3443,
      "columns": [
        "NU_ANO_AVALIACAO",
        "CO_UF",
        "SG_UF",
        "CO_BLOCO",
        "NU_POSICAO",
        "CO_ITEM",
        "TP_SERIE",
        "TP_DISCIPLINA",
        "NU_DESCRITOR_HABILIDADE",
        "DS_GABARITO",
        "TP_RESPOSTA_ITEM",
        "TP_MODELO_TRI",
        "NU_PARAM_A",
        "NU_PARAM_B",
        "NU_PARAM_C",
        "NU_PARAM_B1",
        "NU_PARAM_B2",
        "NU_PARAM_B3",
        "NU_PARAM_B4",
        "IN_ITEM_COMUM"
      ],
      "column_types": {
        "NU_ANO_AVALIACAO": "int64",
        "CO_UF": "int64",
        "SG_UF": "string",
        "CO_BLOCO": "int64",
        "NU_POSICAO": "int64",
        "CO_ITEM": "int64",
        "TP_SERIE": "int64",
        "TP_DISCIPLINA": "int64",
        "NU_DESCRITOR_HABILIDADE": "string",
        "DS_GABARITO": "string",
        "TP_RESPOSTA_ITEM": "int64",
        "TP_MODELO_TRI": "int64",
        "NU_PARAM_A": "double",
        "NU_PARAM_B": "double",
        "NU_PARAM_C": "double",
        "NU_PARAM_B1": "double",
        "NU_PARAM_B2": "double",
        "NU_PARAM_B3": "double",
        "NU_PARAM_B4": "double",
        "IN_ITEM_COMUM": "int64"
      },
      "ano_safra": 2023,
      "table": "TS_ITEM"
    },
    {
      "source": "data/bronze/ano=2023/TS_MUNICIPIO.parquet",
      "target": "data/bronze/ano=2023/TS_MUNICIPIO.parquet",
      "source_size_bytes": 225947,
      "target_size_bytes": 225947,
      "rows": 11547,
      "columns": [
        "NU_ANO_AVALIACAO",
        "CO_UF",
        "SG_UF",
        "CO_MUNICIPIO",
        "NO_MUNICIPIO",
        "TP_SERIE",
        "ID_TIPO_REDE",
        "PC_ALUNO_ALFABETIZADO",
        "VL_MEDIA_LP"
      ],
      "column_types": {
        "NU_ANO_AVALIACAO": "int64",
        "CO_UF": "int64",
        "SG_UF": "string",
        "CO_MUNICIPIO": "int64",
        "NO_MUNICIPIO": "string",
        "TP_SERIE": "int64",
        "ID_TIPO_REDE": "int64",
        "PC_ALUNO_ALFABETIZADO": "double",
        "VL_MEDIA_LP": "double"
      },
      "ano_safra": 2023,
      "table": "TS_MUNICIPIO"
    },
    {
      "source": "data/bronze/ano=2024/TS_ALUNO.parquet",
      "target": "data/bronze/ano=2024/TS_ALUNO.parquet",
      "source_size_bytes": 20580593,
      "target_size_bytes": 20580593,
      "rows": 2120560,
      "columns": [
        "NU_ANO_AVALIACAO",
        "CO_UF",
        "SG_UF",
        "ID_ALUNO",
        "TP_SERIE",
        "ID_ESCOLA",
        "TP_DEPENDENCIA",
        "CO_MUNICIPIO",
        "NO_MUNICIPIO",
        "IN_PRESENCA_LP",
        "IN_PREENCHIMENTO_LP",
        "CO_CADERNO_LP",
        "VL_PESO_ALUNO_LP",
        "VL_PROFICIENCIA_LP",
        "IN_ALFABETIZADO"
      ],
      "column_types": {
        "NU_ANO_AVALIACAO": "int64",
        "CO_UF": "int64",
        "SG_UF": "string",
        "ID_ALUNO": "int64",
        "TP_SERIE": "int64",
        "ID_ESCOLA": "int64",
        "TP_DEPENDENCIA": "int64",
        "CO_MUNICIPIO": "int64",
        "NO_MUNICIPIO": "string",
        "IN_PRESENCA_LP": "int64",
        "IN_PREENCHIMENTO_LP": "int64",
        "CO_CADERNO_LP": "int64",
        "VL_PESO_ALUNO_LP": "double",
        "VL_PROFICIENCIA_LP": "double",
        "IN_ALFABETIZADO": "int64"
      },
      "ano_safra": 2024,
      "table": "TS_ALUNO"
    },
    {
      "source": "data/bronze/ano=2024/TS_ESTADO.parquet",
      "target": "data/bronze/ano=2024/TS_ESTADO.parquet",
      "source_size_bytes": 15725,
      "target_size_bytes": 15725,
      "rows": 75,
      "columns": [
        "NU_ANO_AVALIACAO",
        "CO_UF",
        "SG_UF",
        "TP_SERIE",
        "ID_TIPO_REDE",
        "PC_ALUNO_ALFABETIZADO",
        "VL_MEDIA_LP",
        "PC_ALUNO_NIVEL_0_LP",
        "PC_ALUNO_NIVEL_1_LP",
        "PC_ALUNO_NIVEL_2_LP",
        "PC_ALUNO_NIVEL_3_LP",
        "PC_ALUNO_NIVEL_4_LP",
        "PC_ALUNO_NIVEL_5_LP",
        "PC_ALUNO_NIVEL_6_LP",
        "PC_ALUNO_NIVEL_7_LP",
        "PC_ALUNO_NIVEL_8_LP"
      ],
      "column_types": {
        "NU_ANO_AVALIACAO": "int64",
        "CO_UF": "int64",
        "SG_UF": "string",
        "TP_SERIE": "int64",
        "ID_TIPO_REDE": "int64",
        "PC_ALUNO_ALFABETIZADO": "double",
        "VL_MEDIA_LP": "double",
        "PC_ALUNO_NIVEL_0_LP": "double",
        "PC_ALUNO_NIVEL_1_LP": "double",
        "PC_ALUNO_NIVEL_2_LP": "double",
        "PC_ALUNO_NIVEL_3_LP": "double",
        "PC_ALUNO_NIVEL_4_LP": "double",
        "PC_ALUNO_NIVEL_5_LP": "double",
        "PC_ALUNO_NIVEL_6_LP": "double",
        "PC_ALUNO_NIVEL_7_LP": "double",
        "PC_ALUNO_NIVEL_8_LP": "double"
      },
      "ano_safra": 2024,
      "table": "TS_ESTADO"
    },
    {
      "source": "data/bronze/ano=2024/TS_ITEM.parquet",
      "target": "data/bronze/ano=2024/TS_ITEM.parquet",
      "source_size_bytes": 49972,
      "target_size_bytes": 49972,
      "rows": 1671,
      "columns": [
        "NU_ANO_AVALIACAO",
        "CO_UF",
        "SG_UF",
        "CO_BLOCO",
        "NU_POSICAO",
        "CO_ITEM",
        "TP_SERIE",
        "TP_DISCIPLINA",
        "NU_DESCRITOR_HABILIDADE",
        "DS_GABARITO",
        "TP_RESPOSTA_ITEM",
        "TP_MODELO_TRI",
        "NU_PARAM_A",
        "NU_PARAM_B",
        "NU_PARAM_C",
        "NU_PARAM_B1",
        "NU_PARAM_B2",
        "NU_PARAM_B3",
        "NU_PARAM_B4",
        "IN_ITEM_COMUM"
      ],
      "column_types": {
        "NU_ANO_AVALIACAO": "int64",
        "CO_UF": "int64",
        "SG_UF": "string",
        "CO_BLOCO": "int64",
        "NU_POSICAO": "int64",
        "CO_ITEM": "int64",
        "TP_SERIE": "int64",
        "TP_DISCIPLINA": "int64",
        "NU_DESCRITOR_HABILIDADE": "string",
        "DS_GABARITO": "string",
        "TP_RESPOSTA_ITEM": "int64",
        "TP_MODELO_TRI": "int64",
        "NU_PARAM_A": "double",
        "NU_PARAM_B": "double",
        "NU_PARAM_C": "double",
        "NU_PARAM_B1": "double",
        "NU_PARAM_B2": "double",
        "NU_PARAM_B3": "double",
        "NU_PARAM_B4": "double",
        "IN_ITEM_COMUM": "int64"
      },
      "ano_safra": 2024,
      "table": "TS_ITEM"
    },
    {
      "source": "data/bronze/ano=2024/TS_MUNICIPIO.parquet",
      "target": "data/bronze/ano=2024/TS_MUNICIPIO.parquet",
      "source_size_bytes": 455726,
      "target_size_bytes": 455726,
      "rows": 12448,
      "columns": [
        "NU_ANO_AVALIACAO",
        "CO_UF",
        "SG_UF",
        "CO_MUNICIPIO",
        "NO_MUNICIPIO",
        "TP_SERIE",
        "ID_TIPO_REDE",
        "PC_ALUNO_ALFABETIZADO",
        "VL_MEDIA_LP",
        "PC_ALUNO_NIVEL_0_LP",
        "PC_ALUNO_NIVEL_1_LP",
        "PC_ALUNO_NIVEL_2_LP",
        "PC_ALUNO_NIVEL_3_LP",
        "PC_ALUNO_NIVEL_4_LP",
        "PC_ALUNO_NIVEL_5_LP",
        "PC_ALUNO_NIVEL_6_LP",
        "PC_ALUNO_NIVEL_7_LP",
        "PC_ALUNO_NIVEL_8_LP"
      ],
      "column_types": {
        "NU_ANO_AVALIACAO": "int64",
        "CO_UF": "int64",
        "SG_UF": "string",
        "CO_MUNICIPIO": "int64",
        "NO_MUNICIPIO": "string",
        "TP_SERIE": "int64",
        "ID_TIPO_REDE": "int64",
        "PC_ALUNO_ALFABETIZADO": "double",
        "VL_MEDIA_LP": "double",
        "PC_ALUNO_NIVEL_0_LP": "double",
        "PC_ALUNO_NIVEL_1_LP": "double",
        "PC_ALUNO_NIVEL_2_LP": "double",
        "PC_ALUNO_NIVEL_3_LP": "double",
        "PC_ALUNO_NIVEL_4_LP": "double",
        "PC_ALUNO_NIVEL_5_LP": "double",
        "PC_ALUNO_NIVEL_6_LP": "double",
        "PC_ALUNO_NIVEL_7_LP": "double",
        "PC_ALUNO_NIVEL_8_LP": "double"
      },
      "ano_safra": 2024,
      "table": "TS_MUNICIPIO"
    },
    {
      "source": "data/bronze/ano=2025/TS_ALUNO.parquet",
      "target": "data/bronze/ano=2025/TS_ALUNO.parquet",
      "source_size_bytes": 44564547,
      "target_size_bytes": 44564547,
      "rows": 2222792,
      "columns": [
        "NU_ANO_AVALIACAO",
        "CO_UF",
        "SG_UF",
        "ID_ALUNO",
        "TP_SERIE",
        "ID_ESCOLA",
        "TP_DEPENDENCIA",
        "CO_MUNICIPIO",
        "NO_MUNICIPIO",
        "IN_PRESENCA_LP",
        "IN_PREENCHIMENTO_LP",
        "CO_CADERNO_LP",
        "CO_BLOCO_1",
        "TX_RESPOSTA_BLOCO_1",
        "TX_GABARITO_BLOCO_1",
        "CO_BLOCO_2",
        "TX_RESPOSTA_BLOCO_2",
        "TX_GABARITO_BLOCO_2",
        "CO_BLOCO_3",
        "TX_RESPOSTA_BLOCO_3",
        "TX_GABARITO_BLOCO_3",
        "CO_BLOCO_4",
        "TX_RESPOSTA_BLOCO_4",
        "TX_GABARITO_BLOCO_4",
        "VL_PESO_ALUNO_LP",
        "VL_PROFICIENCIA_LP",
        "IN_ALFABETIZADO"
      ],
      "column_types": {
        "NU_ANO_AVALIACAO": "int64",
        "CO_UF": "int64",
        "SG_UF": "string",
        "ID_ALUNO": "int64",
        "TP_SERIE": "int64",
        "ID_ESCOLA": "double",
        "TP_DEPENDENCIA": "double",
        "CO_MUNICIPIO": "double",
        "NO_MUNICIPIO": "string",
        "IN_PRESENCA_LP": "int64",
        "IN_PREENCHIMENTO_LP": "int64",
        "CO_CADERNO_LP": "int64",
        "CO_BLOCO_1": "double",
        "TX_RESPOSTA_BLOCO_1": "string",
        "TX_GABARITO_BLOCO_1": "string",
        "CO_BLOCO_2": "double",
        "TX_RESPOSTA_BLOCO_2": "string",
        "TX_GABARITO_BLOCO_2": "string",
        "CO_BLOCO_3": "double",
        "TX_RESPOSTA_BLOCO_3": "string",
        "TX_GABARITO_BLOCO_3": "string",
        "CO_BLOCO_4": "double",
        "TX_RESPOSTA_BLOCO_4": "string",
        "TX_GABARITO_BLOCO_4": "string",
        "VL_PESO_ALUNO_LP": "double",
        "VL_PROFICIENCIA_LP": "double",
        "IN_ALFABETIZADO": "int64"
      },
      "ano_safra": 2025,
      "table": "TS_ALUNO"
    },
    {
      "source": "data/bronze/ano=2025/TS_ESTADO.parquet",
      "target": "data/bronze/ano=2025/TS_ESTADO.parquet",
      "source_size_bytes": 16136,
      "target_size_bytes": 16136,
      "rows": 80,
      "columns": [
        "NU_ANO_AVALIACAO",
        "CO_UF",
        "SG_UF",
        "TP_SERIE",
        "ID_TIPO_REDE",
        "PC_ALUNO_ALFABETIZADO",
        "VL_MEDIA_LP",
        "PC_ALUNO_NIVEL_0_LP",
        "PC_ALUNO_NIVEL_1_LP",
        "PC_ALUNO_NIVEL_2_LP",
        "PC_ALUNO_NIVEL_3_LP",
        "PC_ALUNO_NIVEL_4_LP",
        "PC_ALUNO_NIVEL_5_LP",
        "PC_ALUNO_NIVEL_6_LP",
        "PC_ALUNO_NIVEL_7_LP",
        "PC_ALUNO_NIVEL_8_LP"
      ],
      "column_types": {
        "NU_ANO_AVALIACAO": "int64",
        "CO_UF": "int64",
        "SG_UF": "string",
        "TP_SERIE": "int64",
        "ID_TIPO_REDE": "int64",
        "PC_ALUNO_ALFABETIZADO": "double",
        "VL_MEDIA_LP": "double",
        "PC_ALUNO_NIVEL_0_LP": "double",
        "PC_ALUNO_NIVEL_1_LP": "double",
        "PC_ALUNO_NIVEL_2_LP": "double",
        "PC_ALUNO_NIVEL_3_LP": "double",
        "PC_ALUNO_NIVEL_4_LP": "double",
        "PC_ALUNO_NIVEL_5_LP": "double",
        "PC_ALUNO_NIVEL_6_LP": "double",
        "PC_ALUNO_NIVEL_7_LP": "double",
        "PC_ALUNO_NIVEL_8_LP": "double"
      },
      "ano_safra": 2025,
      "table": "TS_ESTADO"
    },
    {
      "source": "data/bronze/ano=2025/TS_ITEM.parquet",
      "target": "data/bronze/ano=2025/TS_ITEM.parquet",
      "source_size_bytes": 58620,
      "target_size_bytes": 58620,
      "rows": 1960,
      "columns": [
        "NU_ANO_AVALIACAO",
        "CO_UF",
        "SG_UF",
        "CO_BLOCO",
        "NU_POSICAO",
        "CO_ITEM",
        "TP_SERIE",
        "TP_DISCIPLINA",
        "NU_DESCRITOR_HABILIDADE",
        "DS_GABARITO",
        "TP_RESPOSTA_ITEM",
        "TP_MODELO_TRI",
        "NU_PARAM_A",
        "NU_PARAM_B",
        "NU_PARAM_C",
        "NU_PARAM_B1",
        "NU_PARAM_B2",
        "NU_PARAM_B3",
        "NU_PARAM_B4",
        "IN_ITEM_COMUM"
      ],
      "column_types": {
        "NU_ANO_AVALIACAO": "int64",
        "CO_UF": "int64",
        "SG_UF": "string",
        "CO_BLOCO": "int64",
        "NU_POSICAO": "int64",
        "CO_ITEM": "int64",
        "TP_SERIE": "int64",
        "TP_DISCIPLINA": "int64",
        "NU_DESCRITOR_HABILIDADE": "string",
        "DS_GABARITO": "string",
        "TP_RESPOSTA_ITEM": "int64",
        "TP_MODELO_TRI": "int64",
        "NU_PARAM_A": "double",
        "NU_PARAM_B": "double",
        "NU_PARAM_C": "double",
        "NU_PARAM_B1": "double",
        "NU_PARAM_B2": "double",
        "NU_PARAM_B3": "double",
        "NU_PARAM_B4": "double",
        "IN_ITEM_COMUM": "int64"
      },
      "ano_safra": 2025,
      "table": "TS_ITEM"
    },
    {
      "source": "data/bronze/ano=2025/TS_MUNICIPIO.parquet",
      "target": "data/bronze/ano=2025/TS_MUNICIPIO.parquet",
      "source_size_bytes": 467557,
      "target_size_bytes": 467557,
      "rows": 12416,
      "columns": [
        "NU_ANO_AVALIACAO",
        "CO_UF",
        "SG_UF",
        "CO_MUNICIPIO",
        "NO_MUNICIPIO",
        "TP_SERIE",
        "ID_TIPO_REDE",
        "PC_ALUNO_ALFABETIZADO",
        "VL_MEDIA_LP",
        "PC_ALUNO_NIVEL_0_LP",
        "PC_ALUNO_NIVEL_1_LP",
        "PC_ALUNO_NIVEL_2_LP",
        "PC_ALUNO_NIVEL_3_LP",
        "PC_ALUNO_NIVEL_4_LP",
        "PC_ALUNO_NIVEL_5_LP",
        "PC_ALUNO_NIVEL_6_LP",
        "PC_ALUNO_NIVEL_7_LP",
        "PC_ALUNO_NIVEL_8_LP"
      ],
      "column_types": {
        "NU_ANO_AVALIACAO": "int64",
        "CO_UF": "int64",
        "SG_UF": "string",
        "CO_MUNICIPIO": "int64",
        "NO_MUNICIPIO": "string",
        "TP_SERIE": "int64",
        "ID_TIPO_REDE": "int64",
        "PC_ALUNO_ALFABETIZADO": "double",
        "VL_MEDIA_LP": "double",
        "PC_ALUNO_NIVEL_0_LP": "double",
        "PC_ALUNO_NIVEL_1_LP": "double",
        "PC_ALUNO_NIVEL_2_LP": "double",
        "PC_ALUNO_NIVEL_3_LP": "double",
        "PC_ALUNO_NIVEL_4_LP": "double",
        "PC_ALUNO_NIVEL_5_LP": "double",
        "PC_ALUNO_NIVEL_6_LP": "double",
        "PC_ALUNO_NIVEL_7_LP": "double",
        "PC_ALUNO_NIVEL_8_LP": "double"
      },
      "ano_safra": 2025,
      "table": "TS_MUNICIPIO"
    },
    {
      "source": "data/bronze/common/br_inep_avaliacao_alfabetizacao_meta_alfabetizacao_brasil.parquet",
      "target": "data/bronze/common/br_inep_avaliacao_alfabetizacao_meta_alfabetizacao_brasil.parquet",
      "source_size_bytes": 7807,
      "target_size_bytes": 7807,
      "rows": 3,
      "columns": [
        "ano",
        "rede",
        "taxa_alfabetizacao",
        "meta_alfabetizacao_2024",
        "meta_alfabetizacao_2025",
        "meta_alfabetizacao_2026",
        "meta_alfabetizacao_2027",
        "meta_alfabetizacao_2028",
        "meta_alfabetizacao_2029",
        "meta_alfabetizacao_2030",
        "percentual_participacao"
      ],
      "column_types": {
        "ano": "int64",
        "rede": "string",
        "taxa_alfabetizacao": "double",
        "meta_alfabetizacao_2024": "double",
        "meta_alfabetizacao_2025": "double",
        "meta_alfabetizacao_2026": "double",
        "meta_alfabetizacao_2027": "double",
        "meta_alfabetizacao_2028": "double",
        "meta_alfabetizacao_2029": "double",
        "meta_alfabetizacao_2030": "int64",
        "percentual_participacao": "double"
      },
      "scope": "common"
    },
    {
      "source": "data/bronze/common/br_inep_avaliacao_alfabetizacao_meta_alfabetizacao_uf.parquet",
      "target": "data/bronze/common/br_inep_avaliacao_alfabetizacao_meta_alfabetizacao_uf.parquet",
      "source_size_bytes": 10014,
      "target_size_bytes": 10014,
      "rows": 54,
      "columns": [
        "ano",
        "sigla_uf",
        "rede",
        "taxa_alfabetizacao",
        "meta_alfabetizacao_2024",
        "meta_alfabetizacao_2025",
        "meta_alfabetizacao_2026",
        "meta_alfabetizacao_2027",
        "meta_alfabetizacao_2028",
        "meta_alfabetizacao_2029",
        "meta_alfabetizacao_2030",
        "percentual_participacao"
      ],
      "column_types": {
        "ano": "int64",
        "sigla_uf": "string",
        "rede": "string",
        "taxa_alfabetizacao": "double",
        "meta_alfabetizacao_2024": "double",
        "meta_alfabetizacao_2025": "double",
        "meta_alfabetizacao_2026": "double",
        "meta_alfabetizacao_2027": "double",
        "meta_alfabetizacao_2028": "double",
        "meta_alfabetizacao_2029": "double",
        "meta_alfabetizacao_2030": "double",
        "percentual_participacao": "double"
      },
      "scope": "common"
    }
  ]
}